byow/__init__.py
byow/llm/__init__.py
byow/llm/ai_model/__init__.py
byow/llm/ai_model/configurations/ModelConfigurations.py
byow/llm/ai_model/configurations/__init__.py
byow/llm/ai_model/model/GPTModel.py
byow/llm/ai_model/model/__init__.py
byow/llm/ai_model_wrapper/GPTAIModel.py
byow/llm/ai_model_wrapper/__init__.py
byow/llm/base_module/__init__.py
byow/llm/base_module/activation/Gelu.py
byow/llm/base_module/activation/__init__.py
byow/llm/base_module/attention/CausalAttention.py
byow/llm/base_module/attention/MultiHeadAttention.py
byow/llm/base_module/attention/SelfAttention.py
byow/llm/base_module/attention/__init__.py
byow/llm/base_module/dataset/SlidingWindowDataSet.py
byow/llm/base_module/dataset/__init__.py
byow/llm/base_module/normalisation/LayerNorm.py
byow/llm/base_module/normalisation/__init__.py
byow/llm/base_module/tokenizer/BaseTokenizer.py
byow/llm/base_module/tokenizer/TikTokenTokenizer.py
byow/llm/base_module/tokenizer/__init__ copy.py
byow/llm/base_module/tokenizer/__init__.py
byow/llm/feedforward/FeedForward.py
byow/llm/feedforward/__init__.py
byow/llm/transformer/TransformerBlock.py
byow/llm/utilities/Utilities.py
byow-1.1.2.dist-info/METADATA
byow-1.1.2.dist-info/WHEEL
byow-1.1.2.dist-info/top_level.txt
byow-1.1.2.dist-info/RECORD
